emailipy/__init__.py
emailipy/cli.py
emailipy/clients.py
emailipy/inliner.py
emailipy/linter.py
emailipy/rules.py
tests/__init__.py
tests/test_inliner.py
emailipy-1.0.1.dist-info/LICENSE
emailipy-1.0.1.dist-info/METADATA
emailipy-1.0.1.dist-info/WHEEL
emailipy-1.0.1.dist-info/entry_points.txt
emailipy-1.0.1.dist-info/top_level.txt
emailipy-1.0.1.dist-info/RECORD
