Metadata-Version: 2.1
Name: emailipy
Version: 1.0.1
Summary: Inlines css into html to make it safe for email.
Home-page: https://github.com/Parsely/emailipy
License-File: LICENSE
Requires-Dist: beautifulsoup4
Requires-Dist: click
Requires-Dist: cssselect
Requires-Dist: lxml
Requires-Dist: tinycss
